{
  "posts": [
    {
      "id": "1",
      "imagesrc": "https://cdn.pixabay.com/photo/2023/08/11/04/51/fireworks-8182800_1280.jpg",
      "title": "Post 1",
      "content": "Lorem ipsum dolor sit amet, consectetur adipiscing elit. Suspendisse at tincidunt ligula. Maecenas et velit vitae quam sollicitudin ullamcorper vitae nec ipsum. Sed vitae ullamcorper elit, sed lacinia libero. Aliquam vestibulum odio vitae nisi feugiat, mattis elementum est commodo. Fusce volutpat accumsan ultricies. Proin dapibus gravida porttitor. Aliquam consequat ex vitae mi tempus, et semper augue dapibus. Vivamus efficitur augue et urna mattis tristique. Sed sed libero justo. Suspendisse non sem convallis, lobortis arcu id, malesuada tortor. Aliquam eu congue libero. Mauris sit amet venenatis libero. Donec vitae purus dui. Sed vehicula ligula ut semper vulputate.Lorem ipsum dolor sit amet, consectetur adipiscing elit. Suspendisse at tincidunt ligula. Maecenas et velit vitae quam sollicitudin ullamcorper vitae nec ipsum. Sed vitae ullamcorper elit, sed lacinia libero. Aliquam vestibulum odio vitae nisi feugiat, mattis elementum est commodo. Fusce volutpat accumsan ultricies. Proin dapibus gravida porttitor. Aliquam consequat ex vitae mi tempus, et semper augue dapibus. Vivamus efficitur augue et urna mattis tristique. Sed sed libero justo. Suspendisse non sem convallis, lobortis arcu id, malesuada tortor. Aliquam eu congue libero. Mauris sit amet venenatis libero. Donec vitae purus dui. Sed vehicula ligula ut semper vulputate.Lorem ipsum dolor sit amet, consectetur adipiscing elit. Suspendisse at tincidunt ligula. Maecenas et velit vitae quam sollicitudin ullamcorper vitae nec ipsum. Sed vitae ullamcorper elit, sed lacinia libero. Aliquam vestibulum odio vitae nisi feugiat, mattis elementum est commodo. Fusce volutpat accumsan ultricies. Proin dapibus gravida porttitor. Aliquam consequat ex vitae mi tempus, et semper augue dapibus. Vivamus efficitur augue et urna mattis tristique. Sed sed libero justo. Suspendisse non sem convallis, lobortis arcu id, malesuada tortor. Aliquam eu congue libero. Mauris sit amet venenatis libero. Donec vitae purus dui. Sed vehicula ligula ut semper vulputate.Lorem ipsum dolor sit amet, consectetur adipiscing elit. Suspendisse at tincidunt ligula. Maecenas et velit vitae quam sollicitudin ullamcorper vitae nec ipsum. Sed vitae ullamcorper elit, sed lacinia libero. Aliquam vestibulum odio vitae nisi feugiat, mattis elementum est commodo. Fusce volutpat accumsan ultricies. Proin dapibus gravida porttitor. Aliquam consequat ex vitae mi tempus, et semper augue dapibus. Vivamus efficitur augue et urna mattis tristique. Sed sed libero justo. Suspendisse non sem convallis, lobortis arcu id, malesuada tortor. Aliquam eu congue libero. Mauris sit amet venenatis libero. Donec vitae purus dui. Sed vehicula ligula ut semper vulputate.Lorem ipsum dolor sit amet, consectetur adipiscing elit. Suspendisse at tincidunt ligula. Maecenas et velit vitae quam sollicitudin ullamcorper vitae nec ipsum. Sed vitae ullamcorper elit, sed lacinia libero. Aliquam vestibulum odio vitae nisi feugiat, mattis elementum est commodo. Fusce volutpat accumsan ultricies. Proin dapibus gravida porttitor. Aliquam consequat ex vitae mi tempus, et semper augue dapibus. Vivamus efficitur augue et urna mattis tristique. Sed sed libero justo. Suspendisse non sem convallis, lobortis arcu id, malesuada tortor. Aliquam eu congue libero. Mauris sit amet venenatis libero. Donec vitae purus dui. Sed vehicula ligula ut semper vulputate.Lorem ipsum dolor sit amet, consectetur adipiscing elit. Suspendisse at tincidunt ligula. Maecenas et velit vitae quam sollicitudin ullamcorper vitae nec ipsum. Sed vitae ullamcorper elit, sed lacinia libero. Aliquam vestibulum odio vitae nisi feugiat, mattis elementum est commodo. Fusce volutpat accumsan ultricies. Proin dapibus gravida porttitor. Aliquam consequat ex vitae mi tempus, et semper augue dapibus. Vivamus efficitur augue et urna mattis tristique. Sed sed libero justo. Suspendisse non sem convallis, lobortis arcu id, malesuada tortor. Aliquam eu congue libero. Mauris sit amet venenatis libero. Donec vitae purus dui. Sed vehicula ligula ut semper vulputate."
    },
    {
      "id": "2",
      "imagesrc": "https://cdn.pixabay.com/photo/2023/08/11/04/51/fireworks-8182800_1280.jpg",
      "title": "Post 1",
      "content": "Lorem ipsum dolor sit amet, consectetur adipiscing elit. Suspendisse at tincidunt ligula. Maecenas et velit vitae quam sollicitudin ullamcorper vitae nec ipsum. Sed vitae ullamcorper elit, sed lacinia libero. Aliquam vestibulum odio vitae nisi feugiat, mattis elementum est commodo. Fusce volutpat accumsan ultricies. Proin dapibus gravida porttitor. Aliquam consequat ex vitae mi tempus, et semper augue dapibus. Vivamus efficitur augue et urna mattis tristique. Sed sed libero justo. Suspendisse non sem convallis, lobortis arcu id, malesuada tortor. Aliquam eu congue libero. Mauris sit amet venenatis libero. Donec vitae purus dui. Sed vehicula ligula ut semper vulputate.Lorem ipsum dolor sit amet, consectetur adipiscing elit. Suspendisse at tincidunt ligula. Maecenas et velit vitae quam sollicitudin ullamcorper vitae nec ipsum. Sed vitae ullamcorper elit, sed lacinia libero. Aliquam vestibulum odio vitae nisi feugiat, mattis elementum est commodo. Fusce volutpat accumsan ultricies. Proin dapibus gravida porttitor. Aliquam consequat ex vitae mi tempus, et semper augue dapibus. Vivamus efficitur augue et urna mattis tristique. Sed sed libero justo. Suspendisse non sem convallis, lobortis arcu id, malesuada tortor. Aliquam eu congue libero. Mauris sit amet venenatis libero. Donec vitae purus dui. Sed vehicula ligula ut semper vulputate.Lorem ipsum dolor sit amet, consectetur adipiscing elit. Suspendisse at tincidunt ligula. Maecenas et velit vitae quam sollicitudin ullamcorper vitae nec ipsum. Sed vitae ullamcorper elit, sed lacinia libero. Aliquam vestibulum odio vitae nisi feugiat, mattis elementum est commodo. Fusce volutpat accumsan ultricies. Proin dapibus gravida porttitor. Aliquam consequat ex vitae mi tempus, et semper augue dapibus. Vivamus efficitur augue et urna mattis tristique. Sed sed libero justo. Suspendisse non sem convallis, lobortis arcu id, malesuada tortor. Aliquam eu congue libero. Mauris sit amet venenatis libero. Donec vitae purus dui. Sed vehicula ligula ut semper vulputate.Lorem ipsum dolor sit amet, consectetur adipiscing elit. Suspendisse at tincidunt ligula. Maecenas et velit vitae quam sollicitudin ullamcorper vitae nec ipsum. Sed vitae ullamcorper elit, sed lacinia libero. Aliquam vestibulum odio vitae nisi feugiat, mattis elementum est commodo. Fusce volutpat accumsan ultricies. Proin dapibus gravida porttitor. Aliquam consequat ex vitae mi tempus, et semper augue dapibus. Vivamus efficitur augue et urna mattis tristique. Sed sed libero justo. Suspendisse non sem convallis, lobortis arcu id, malesuada tortor. Aliquam eu congue libero. Mauris sit amet venenatis libero. Donec vitae purus dui. Sed vehicula ligula ut semper vulputate.Lorem ipsum dolor sit amet, consectetur adipiscing elit. Suspendisse at tincidunt ligula. Maecenas et velit vitae quam sollicitudin ullamcorper vitae nec ipsum. Sed vitae ullamcorper elit, sed lacinia libero. Aliquam vestibulum odio vitae nisi feugiat, mattis elementum est commodo. Fusce volutpat accumsan ultricies. Proin dapibus gravida porttitor. Aliquam consequat ex vitae mi tempus, et semper augue dapibus. Vivamus efficitur augue et urna mattis tristique. Sed sed libero justo. Suspendisse non sem convallis, lobortis arcu id, malesuada tortor. Aliquam eu congue libero. Mauris sit amet venenatis libero. Donec vitae purus dui. Sed vehicula ligula ut semper vulputate.Lorem ipsum dolor sit amet, consectetur adipiscing elit. Suspendisse at tincidunt ligula. Maecenas et velit vitae quam sollicitudin ullamcorper vitae nec ipsum. Sed vitae ullamcorper elit, sed lacinia libero. Aliquam vestibulum odio vitae nisi feugiat, mattis elementum est commodo. Fusce volutpat accumsan ultricies. Proin dapibus gravida porttitor. Aliquam consequat ex vitae mi tempus, et semper augue dapibus. Vivamus efficitur augue et urna mattis tristique. Sed sed libero justo. Suspendisse non sem convallis, lobortis arcu id, malesuada tortor. Aliquam eu congue libero. Mauris sit amet venenatis libero. Donec vitae purus dui. Sed vehicula ligula ut semper vulputate."
    },
    {
      "id": "3",
      "imagesrc": "https://cdn.pixabay.com/photo/2023/08/11/04/51/fireworks-8182800_1280.jpg",
      "title": "Post 1",
      "content": "Lorem ipsum dolor sit amet, consectetur adipiscing elit. Suspendisse at tincidunt ligula. Maecenas et velit vitae quam sollicitudin ullamcorper vitae nec ipsum. Sed vitae ullamcorper elit, sed lacinia libero. Aliquam vestibulum odio vitae nisi feugiat, mattis elementum est commodo. Fusce volutpat accumsan ultricies. Proin dapibus gravida porttitor. Aliquam consequat ex vitae mi tempus, et semper augue dapibus. Vivamus efficitur augue et urna mattis tristique. Sed sed libero justo. Suspendisse non sem convallis, lobortis arcu id, malesuada tortor. Aliquam eu congue libero. Mauris sit amet venenatis libero. Donec vitae purus dui. Sed vehicula ligula ut semper vulputate.Lorem ipsum dolor sit amet, consectetur adipiscing elit. Suspendisse at tincidunt ligula. Maecenas et velit vitae quam sollicitudin ullamcorper vitae nec ipsum. Sed vitae ullamcorper elit, sed lacinia libero. Aliquam vestibulum odio vitae nisi feugiat, mattis elementum est commodo. Fusce volutpat accumsan ultricies. Proin dapibus gravida porttitor. Aliquam consequat ex vitae mi tempus, et semper augue dapibus. Vivamus efficitur augue et urna mattis tristique. Sed sed libero justo. Suspendisse non sem convallis, lobortis arcu id, malesuada tortor. Aliquam eu congue libero. Mauris sit amet venenatis libero. Donec vitae purus dui. Sed vehicula ligula ut semper vulputate.Lorem ipsum dolor sit amet, consectetur adipiscing elit. Suspendisse at tincidunt ligula. Maecenas et velit vitae quam sollicitudin ullamcorper vitae nec ipsum. Sed vitae ullamcorper elit, sed lacinia libero. Aliquam vestibulum odio vitae nisi feugiat, mattis elementum est commodo. Fusce volutpat accumsan ultricies. Proin dapibus gravida porttitor. Aliquam consequat ex vitae mi tempus, et semper augue dapibus. Vivamus efficitur augue et urna mattis tristique. Sed sed libero justo. Suspendisse non sem convallis, lobortis arcu id, malesuada tortor. Aliquam eu congue libero. Mauris sit amet venenatis libero. Donec vitae purus dui. Sed vehicula ligula ut semper vulputate.Lorem ipsum dolor sit amet, consectetur adipiscing elit. Suspendisse at tincidunt ligula. Maecenas et velit vitae quam sollicitudin ullamcorper vitae nec ipsum. Sed vitae ullamcorper elit, sed lacinia libero. Aliquam vestibulum odio vitae nisi feugiat, mattis elementum est commodo. Fusce volutpat accumsan ultricies. Proin dapibus gravida porttitor. Aliquam consequat ex vitae mi tempus, et semper augue dapibus. Vivamus efficitur augue et urna mattis tristique. Sed sed libero justo. Suspendisse non sem convallis, lobortis arcu id, malesuada tortor. Aliquam eu congue libero. Mauris sit amet venenatis libero. Donec vitae purus dui. Sed vehicula ligula ut semper vulputate.Lorem ipsum dolor sit amet, consectetur adipiscing elit. Suspendisse at tincidunt ligula. Maecenas et velit vitae quam sollicitudin ullamcorper vitae nec ipsum. Sed vitae ullamcorper elit, sed lacinia libero. Aliquam vestibulum odio vitae nisi feugiat, mattis elementum est commodo. Fusce volutpat accumsan ultricies. Proin dapibus gravida porttitor. Aliquam consequat ex vitae mi tempus, et semper augue dapibus. Vivamus efficitur augue et urna mattis tristique. Sed sed libero justo. Suspendisse non sem convallis, lobortis arcu id, malesuada tortor. Aliquam eu congue libero. Mauris sit amet venenatis libero. Donec vitae purus dui. Sed vehicula ligula ut semper vulputate.Lorem ipsum dolor sit amet, consectetur adipiscing elit. Suspendisse at tincidunt ligula. Maecenas et velit vitae quam sollicitudin ullamcorper vitae nec ipsum. Sed vitae ullamcorper elit, sed lacinia libero. Aliquam vestibulum odio vitae nisi feugiat, mattis elementum est commodo. Fusce volutpat accumsan ultricies. Proin dapibus gravida porttitor. Aliquam consequat ex vitae mi tempus, et semper augue dapibus. Vivamus efficitur augue et urna mattis tristique. Sed sed libero justo. Suspendisse non sem convallis, lobortis arcu id, malesuada tortor. Aliquam eu congue libero. Mauris sit amet venenatis libero. Donec vitae purus dui. Sed vehicula ligula ut semper vulputate."
    },
    {
      "id": "4",
      "imagesrc": "https://cdn.pixabay.com/photo/2023/08/11/04/51/fireworks-8182800_1280.jpg",
      "title": "Post 1",
      "content": "Lorem ipsum dolor sit amet, consectetur adipiscing elit. Suspendisse at tincidunt ligula. Maecenas et velit vitae quam sollicitudin ullamcorper vitae nec ipsum. Sed vitae ullamcorper elit, sed lacinia libero. Aliquam vestibulum odio vitae nisi feugiat, mattis elementum est commodo. Fusce volutpat accumsan ultricies. Proin dapibus gravida porttitor. Aliquam consequat ex vitae mi tempus, et semper augue dapibus. Vivamus efficitur augue et urna mattis tristique. Sed sed libero justo. Suspendisse non sem convallis, lobortis arcu id, malesuada tortor. Aliquam eu congue libero. Mauris sit amet venenatis libero. Donec vitae purus dui. Sed vehicula ligula ut semper vulputate.Lorem ipsum dolor sit amet, consectetur adipiscing elit. Suspendisse at tincidunt ligula. Maecenas et velit vitae quam sollicitudin ullamcorper vitae nec ipsum. Sed vitae ullamcorper elit, sed lacinia libero. Aliquam vestibulum odio vitae nisi feugiat, mattis elementum est commodo. Fusce volutpat accumsan ultricies. Proin dapibus gravida porttitor. Aliquam consequat ex vitae mi tempus, et semper augue dapibus. Vivamus efficitur augue et urna mattis tristique. Sed sed libero justo. Suspendisse non sem convallis, lobortis arcu id, malesuada tortor. Aliquam eu congue libero. Mauris sit amet venenatis libero. Donec vitae purus dui. Sed vehicula ligula ut semper vulputate.Lorem ipsum dolor sit amet, consectetur adipiscing elit. Suspendisse at tincidunt ligula. Maecenas et velit vitae quam sollicitudin ullamcorper vitae nec ipsum. Sed vitae ullamcorper elit, sed lacinia libero. Aliquam vestibulum odio vitae nisi feugiat, mattis elementum est commodo. Fusce volutpat accumsan ultricies. Proin dapibus gravida porttitor. Aliquam consequat ex vitae mi tempus, et semper augue dapibus. Vivamus efficitur augue et urna mattis tristique. Sed sed libero justo. Suspendisse non sem convallis, lobortis arcu id, malesuada tortor. Aliquam eu congue libero. Mauris sit amet venenatis libero. Donec vitae purus dui. Sed vehicula ligula ut semper vulputate.Lorem ipsum dolor sit amet, consectetur adipiscing elit. Suspendisse at tincidunt ligula. Maecenas et velit vitae quam sollicitudin ullamcorper vitae nec ipsum. Sed vitae ullamcorper elit, sed lacinia libero. Aliquam vestibulum odio vitae nisi feugiat, mattis elementum est commodo. Fusce volutpat accumsan ultricies. Proin dapibus gravida porttitor. Aliquam consequat ex vitae mi tempus, et semper augue dapibus. Vivamus efficitur augue et urna mattis tristique. Sed sed libero justo. Suspendisse non sem convallis, lobortis arcu id, malesuada tortor. Aliquam eu congue libero. Mauris sit amet venenatis libero. Donec vitae purus dui. Sed vehicula ligula ut semper vulputate.Lorem ipsum dolor sit amet, consectetur adipiscing elit. Suspendisse at tincidunt ligula. Maecenas et velit vitae quam sollicitudin ullamcorper vitae nec ipsum. Sed vitae ullamcorper elit, sed lacinia libero. Aliquam vestibulum odio vitae nisi feugiat, mattis elementum est commodo. Fusce volutpat accumsan ultricies. Proin dapibus gravida porttitor. Aliquam consequat ex vitae mi tempus, et semper augue dapibus. Vivamus efficitur augue et urna mattis tristique. Sed sed libero justo. Suspendisse non sem convallis, lobortis arcu id, malesuada tortor. Aliquam eu congue libero. Mauris sit amet venenatis libero. Donec vitae purus dui. Sed vehicula ligula ut semper vulputate.Lorem ipsum dolor sit amet, consectetur adipiscing elit. Suspendisse at tincidunt ligula. Maecenas et velit vitae quam sollicitudin ullamcorper vitae nec ipsum. Sed vitae ullamcorper elit, sed lacinia libero. Aliquam vestibulum odio vitae nisi feugiat, mattis elementum est commodo. Fusce volutpat accumsan ultricies. Proin dapibus gravida porttitor. Aliquam consequat ex vitae mi tempus, et semper augue dapibus. Vivamus efficitur augue et urna mattis tristique. Sed sed libero justo. Suspendisse non sem convallis, lobortis arcu id, malesuada tortor. Aliquam eu congue libero. Mauris sit amet venenatis libero. Donec vitae purus dui. Sed vehicula ligula ut semper vulputate."
    },
    {
      "id": "5",
      "imagesrc": "https://cdn.pixabay.com/photo/2023/08/11/04/51/fireworks-8182800_1280.jpg",
      "title": "Post 1",
      "content": "Lorem ipsum dolor sit amet, consectetur adipiscing elit. Suspendisse at tincidunt ligula. Maecenas et velit vitae quam sollicitudin ullamcorper vitae nec ipsum. Sed vitae ullamcorper elit, sed lacinia libero. Aliquam vestibulum odio vitae nisi feugiat, mattis elementum est commodo. Fusce volutpat accumsan ultricies. Proin dapibus gravida porttitor. Aliquam consequat ex vitae mi tempus, et semper augue dapibus. Vivamus efficitur augue et urna mattis tristique. Sed sed libero justo. Suspendisse non sem convallis, lobortis arcu id, malesuada tortor. Aliquam eu congue libero. Mauris sit amet venenatis libero. Donec vitae purus dui. Sed vehicula ligula ut semper vulputate.Lorem ipsum dolor sit amet, consectetur adipiscing elit. Suspendisse at tincidunt ligula. Maecenas et velit vitae quam sollicitudin ullamcorper vitae nec ipsum. Sed vitae ullamcorper elit, sed lacinia libero. Aliquam vestibulum odio vitae nisi feugiat, mattis elementum est commodo. Fusce volutpat accumsan ultricies. Proin dapibus gravida porttitor. Aliquam consequat ex vitae mi tempus, et semper augue dapibus. Vivamus efficitur augue et urna mattis tristique. Sed sed libero justo. Suspendisse non sem convallis, lobortis arcu id, malesuada tortor. Aliquam eu congue libero. Mauris sit amet venenatis libero. Donec vitae purus dui. Sed vehicula ligula ut semper vulputate.Lorem ipsum dolor sit amet, consectetur adipiscing elit. Suspendisse at tincidunt ligula. Maecenas et velit vitae quam sollicitudin ullamcorper vitae nec ipsum. Sed vitae ullamcorper elit, sed lacinia libero. Aliquam vestibulum odio vitae nisi feugiat, mattis elementum est commodo. Fusce volutpat accumsan ultricies. Proin dapibus gravida porttitor. Aliquam consequat ex vitae mi tempus, et semper augue dapibus. Vivamus efficitur augue et urna mattis tristique. Sed sed libero justo. Suspendisse non sem convallis, lobortis arcu id, malesuada tortor. Aliquam eu congue libero. Mauris sit amet venenatis libero. Donec vitae purus dui. Sed vehicula ligula ut semper vulputate.Lorem ipsum dolor sit amet, consectetur adipiscing elit. Suspendisse at tincidunt ligula. Maecenas et velit vitae quam sollicitudin ullamcorper vitae nec ipsum. Sed vitae ullamcorper elit, sed lacinia libero. Aliquam vestibulum odio vitae nisi feugiat, mattis elementum est commodo. Fusce volutpat accumsan ultricies. Proin dapibus gravida porttitor. Aliquam consequat ex vitae mi tempus, et semper augue dapibus. Vivamus efficitur augue et urna mattis tristique. Sed sed libero justo. Suspendisse non sem convallis, lobortis arcu id, malesuada tortor. Aliquam eu congue libero. Mauris sit amet venenatis libero. Donec vitae purus dui. Sed vehicula ligula ut semper vulputate.Lorem ipsum dolor sit amet, consectetur adipiscing elit. Suspendisse at tincidunt ligula. Maecenas et velit vitae quam sollicitudin ullamcorper vitae nec ipsum. Sed vitae ullamcorper elit, sed lacinia libero. Aliquam vestibulum odio vitae nisi feugiat, mattis elementum est commodo. Fusce volutpat accumsan ultricies. Proin dapibus gravida porttitor. Aliquam consequat ex vitae mi tempus, et semper augue dapibus. Vivamus efficitur augue et urna mattis tristique. Sed sed libero justo. Suspendisse non sem convallis, lobortis arcu id, malesuada tortor. Aliquam eu congue libero. Mauris sit amet venenatis libero. Donec vitae purus dui. Sed vehicula ligula ut semper vulputate.Lorem ipsum dolor sit amet, consectetur adipiscing elit. Suspendisse at tincidunt ligula. Maecenas et velit vitae quam sollicitudin ullamcorper vitae nec ipsum. Sed vitae ullamcorper elit, sed lacinia libero. Aliquam vestibulum odio vitae nisi feugiat, mattis elementum est commodo. Fusce volutpat accumsan ultricies. Proin dapibus gravida porttitor. Aliquam consequat ex vitae mi tempus, et semper augue dapibus. Vivamus efficitur augue et urna mattis tristique. Sed sed libero justo. Suspendisse non sem convallis, lobortis arcu id, malesuada tortor. Aliquam eu congue libero. Mauris sit amet venenatis libero. Donec vitae purus dui. Sed vehicula ligula ut semper vulputate."
    },
    {
      "id": "6",
      "imagesrc": "https://cdn.pixabay.com/photo/2023/08/11/04/51/fireworks-8182800_1280.jpg",
      "title": "Post 1",
      "content": "Lorem ipsum dolor sit amet, consectetur adipiscing elit. Suspendisse at tincidunt ligula. Maecenas et velit vitae quam sollicitudin ullamcorper vitae nec ipsum. Sed vitae ullamcorper elit, sed lacinia libero. Aliquam vestibulum odio vitae nisi feugiat, mattis elementum est commodo. Fusce volutpat accumsan ultricies. Proin dapibus gravida porttitor. Aliquam consequat ex vitae mi tempus, et semper augue dapibus. Vivamus efficitur augue et urna mattis tristique. Sed sed libero justo. Suspendisse non sem convallis, lobortis arcu id, malesuada tortor. Aliquam eu congue libero. Mauris sit amet venenatis libero. Donec vitae purus dui. Sed vehicula ligula ut semper vulputate.Lorem ipsum dolor sit amet, consectetur adipiscing elit. Suspendisse at tincidunt ligula. Maecenas et velit vitae quam sollicitudin ullamcorper vitae nec ipsum. Sed vitae ullamcorper elit, sed lacinia libero. Aliquam vestibulum odio vitae nisi feugiat, mattis elementum est commodo. Fusce volutpat accumsan ultricies. Proin dapibus gravida porttitor. Aliquam consequat ex vitae mi tempus, et semper augue dapibus. Vivamus efficitur augue et urna mattis tristique. Sed sed libero justo. Suspendisse non sem convallis, lobortis arcu id, malesuada tortor. Aliquam eu congue libero. Mauris sit amet venenatis libero. Donec vitae purus dui. Sed vehicula ligula ut semper vulputate.Lorem ipsum dolor sit amet, consectetur adipiscing elit. Suspendisse at tincidunt ligula. Maecenas et velit vitae quam sollicitudin ullamcorper vitae nec ipsum. Sed vitae ullamcorper elit, sed lacinia libero. Aliquam vestibulum odio vitae nisi feugiat, mattis elementum est commodo. Fusce volutpat accumsan ultricies. Proin dapibus gravida porttitor. Aliquam consequat ex vitae mi tempus, et semper augue dapibus. Vivamus efficitur augue et urna mattis tristique. Sed sed libero justo. Suspendisse non sem convallis, lobortis arcu id, malesuada tortor. Aliquam eu congue libero. Mauris sit amet venenatis libero. Donec vitae purus dui. Sed vehicula ligula ut semper vulputate.Lorem ipsum dolor sit amet, consectetur adipiscing elit. Suspendisse at tincidunt ligula. Maecenas et velit vitae quam sollicitudin ullamcorper vitae nec ipsum. Sed vitae ullamcorper elit, sed lacinia libero. Aliquam vestibulum odio vitae nisi feugiat, mattis elementum est commodo. Fusce volutpat accumsan ultricies. Proin dapibus gravida porttitor. Aliquam consequat ex vitae mi tempus, et semper augue dapibus. Vivamus efficitur augue et urna mattis tristique. Sed sed libero justo. Suspendisse non sem convallis, lobortis arcu id, malesuada tortor. Aliquam eu congue libero. Mauris sit amet venenatis libero. Donec vitae purus dui. Sed vehicula ligula ut semper vulputate.Lorem ipsum dolor sit amet, consectetur adipiscing elit. Suspendisse at tincidunt ligula. Maecenas et velit vitae quam sollicitudin ullamcorper vitae nec ipsum. Sed vitae ullamcorper elit, sed lacinia libero. Aliquam vestibulum odio vitae nisi feugiat, mattis elementum est commodo. Fusce volutpat accumsan ultricies. Proin dapibus gravida porttitor. Aliquam consequat ex vitae mi tempus, et semper augue dapibus. Vivamus efficitur augue et urna mattis tristique. Sed sed libero justo. Suspendisse non sem convallis, lobortis arcu id, malesuada tortor. Aliquam eu congue libero. Mauris sit amet venenatis libero. Donec vitae purus dui. Sed vehicula ligula ut semper vulputate.Lorem ipsum dolor sit amet, consectetur adipiscing elit. Suspendisse at tincidunt ligula. Maecenas et velit vitae quam sollicitudin ullamcorper vitae nec ipsum. Sed vitae ullamcorper elit, sed lacinia libero. Aliquam vestibulum odio vitae nisi feugiat, mattis elementum est commodo. Fusce volutpat accumsan ultricies. Proin dapibus gravida porttitor. Aliquam consequat ex vitae mi tempus, et semper augue dapibus. Vivamus efficitur augue et urna mattis tristique. Sed sed libero justo. Suspendisse non sem convallis, lobortis arcu id, malesuada tortor. Aliquam eu congue libero. Mauris sit amet venenatis libero. Donec vitae purus dui. Sed vehicula ligula ut semper vulputate."
    },
    {
      "id": "7",
      "imagesrc": "https://cdn.pixabay.com/photo/2023/08/11/04/51/fireworks-8182800_1280.jpg",
      "title": "Post 1",
      "content": "Lorem ipsum dolor sit amet, consectetur adipiscing elit. Suspendisse at tincidunt ligula. Maecenas et velit vitae quam sollicitudin ullamcorper vitae nec ipsum. Sed vitae ullamcorper elit, sed lacinia libero. Aliquam vestibulum odio vitae nisi feugiat, mattis elementum est commodo. Fusce volutpat accumsan ultricies. Proin dapibus gravida porttitor. Aliquam consequat ex vitae mi tempus, et semper augue dapibus. Vivamus efficitur augue et urna mattis tristique. Sed sed libero justo. Suspendisse non sem convallis, lobortis arcu id, malesuada tortor. Aliquam eu congue libero. Mauris sit amet venenatis libero. Donec vitae purus dui. Sed vehicula ligula ut semper vulputate.Lorem ipsum dolor sit amet, consectetur adipiscing elit. Suspendisse at tincidunt ligula. Maecenas et velit vitae quam sollicitudin ullamcorper vitae nec ipsum. Sed vitae ullamcorper elit, sed lacinia libero. Aliquam vestibulum odio vitae nisi feugiat, mattis elementum est commodo. Fusce volutpat accumsan ultricies. Proin dapibus gravida porttitor. Aliquam consequat ex vitae mi tempus, et semper augue dapibus. Vivamus efficitur augue et urna mattis tristique. Sed sed libero justo. Suspendisse non sem convallis, lobortis arcu id, malesuada tortor. Aliquam eu congue libero. Mauris sit amet venenatis libero. Donec vitae purus dui. Sed vehicula ligula ut semper vulputate.Lorem ipsum dolor sit amet, consectetur adipiscing elit. Suspendisse at tincidunt ligula. Maecenas et velit vitae quam sollicitudin ullamcorper vitae nec ipsum. Sed vitae ullamcorper elit, sed lacinia libero. Aliquam vestibulum odio vitae nisi feugiat, mattis elementum est commodo. Fusce volutpat accumsan ultricies. Proin dapibus gravida porttitor. Aliquam consequat ex vitae mi tempus, et semper augue dapibus. Vivamus efficitur augue et urna mattis tristique. Sed sed libero justo. Suspendisse non sem convallis, lobortis arcu id, malesuada tortor. Aliquam eu congue libero. Mauris sit amet venenatis libero. Donec vitae purus dui. Sed vehicula ligula ut semper vulputate.Lorem ipsum dolor sit amet, consectetur adipiscing elit. Suspendisse at tincidunt ligula. Maecenas et velit vitae quam sollicitudin ullamcorper vitae nec ipsum. Sed vitae ullamcorper elit, sed lacinia libero. Aliquam vestibulum odio vitae nisi feugiat, mattis elementum est commodo. Fusce volutpat accumsan ultricies. Proin dapibus gravida porttitor. Aliquam consequat ex vitae mi tempus, et semper augue dapibus. Vivamus efficitur augue et urna mattis tristique. Sed sed libero justo. Suspendisse non sem convallis, lobortis arcu id, malesuada tortor. Aliquam eu congue libero. Mauris sit amet venenatis libero. Donec vitae purus dui. Sed vehicula ligula ut semper vulputate.Lorem ipsum dolor sit amet, consectetur adipiscing elit. Suspendisse at tincidunt ligula. Maecenas et velit vitae quam sollicitudin ullamcorper vitae nec ipsum. Sed vitae ullamcorper elit, sed lacinia libero. Aliquam vestibulum odio vitae nisi feugiat, mattis elementum est commodo. Fusce volutpat accumsan ultricies. Proin dapibus gravida porttitor. Aliquam consequat ex vitae mi tempus, et semper augue dapibus. Vivamus efficitur augue et urna mattis tristique. Sed sed libero justo. Suspendisse non sem convallis, lobortis arcu id, malesuada tortor. Aliquam eu congue libero. Mauris sit amet venenatis libero. Donec vitae purus dui. Sed vehicula ligula ut semper vulputate.Lorem ipsum dolor sit amet, consectetur adipiscing elit. Suspendisse at tincidunt ligula. Maecenas et velit vitae quam sollicitudin ullamcorper vitae nec ipsum. Sed vitae ullamcorper elit, sed lacinia libero. Aliquam vestibulum odio vitae nisi feugiat, mattis elementum est commodo. Fusce volutpat accumsan ultricies. Proin dapibus gravida porttitor. Aliquam consequat ex vitae mi tempus, et semper augue dapibus. Vivamus efficitur augue et urna mattis tristique. Sed sed libero justo. Suspendisse non sem convallis, lobortis arcu id, malesuada tortor. Aliquam eu congue libero. Mauris sit amet venenatis libero. Donec vitae purus dui. Sed vehicula ligula ut semper vulputate."
    },
    {
      "id": "8",
      "imagesrc": "https://cdn.pixabay.com/photo/2023/08/11/04/51/fireworks-8182800_1280.jpg",
      "title": "Post 1",
      "content": "Lorem ipsum dolor sit amet, consectetur adipiscing elit. Suspendisse at tincidunt ligula. Maecenas et velit vitae quam sollicitudin ullamcorper vitae nec ipsum. Sed vitae ullamcorper elit, sed lacinia libero. Aliquam vestibulum odio vitae nisi feugiat, mattis elementum est commodo. Fusce volutpat accumsan ultricies. Proin dapibus gravida porttitor. Aliquam consequat ex vitae mi tempus, et semper augue dapibus. Vivamus efficitur augue et urna mattis tristique. Sed sed libero justo. Suspendisse non sem convallis, lobortis arcu id, malesuada tortor. Aliquam eu congue libero. Mauris sit amet venenatis libero. Donec vitae purus dui. Sed vehicula ligula ut semper vulputate.Lorem ipsum dolor sit amet, consectetur adipiscing elit. Suspendisse at tincidunt ligula. Maecenas et velit vitae quam sollicitudin ullamcorper vitae nec ipsum. Sed vitae ullamcorper elit, sed lacinia libero. Aliquam vestibulum odio vitae nisi feugiat, mattis elementum est commodo. Fusce volutpat accumsan ultricies. Proin dapibus gravida porttitor. Aliquam consequat ex vitae mi tempus, et semper augue dapibus. Vivamus efficitur augue et urna mattis tristique. Sed sed libero justo. Suspendisse non sem convallis, lobortis arcu id, malesuada tortor. Aliquam eu congue libero. Mauris sit amet venenatis libero. Donec vitae purus dui. Sed vehicula ligula ut semper vulputate.Lorem ipsum dolor sit amet, consectetur adipiscing elit. Suspendisse at tincidunt ligula. Maecenas et velit vitae quam sollicitudin ullamcorper vitae nec ipsum. Sed vitae ullamcorper elit, sed lacinia libero. Aliquam vestibulum odio vitae nisi feugiat, mattis elementum est commodo. Fusce volutpat accumsan ultricies. Proin dapibus gravida porttitor. Aliquam consequat ex vitae mi tempus, et semper augue dapibus. Vivamus efficitur augue et urna mattis tristique. Sed sed libero justo. Suspendisse non sem convallis, lobortis arcu id, malesuada tortor. Aliquam eu congue libero. Mauris sit amet venenatis libero. Donec vitae purus dui. Sed vehicula ligula ut semper vulputate.Lorem ipsum dolor sit amet, consectetur adipiscing elit. Suspendisse at tincidunt ligula. Maecenas et velit vitae quam sollicitudin ullamcorper vitae nec ipsum. Sed vitae ullamcorper elit, sed lacinia libero. Aliquam vestibulum odio vitae nisi feugiat, mattis elementum est commodo. Fusce volutpat accumsan ultricies. Proin dapibus gravida porttitor. Aliquam consequat ex vitae mi tempus, et semper augue dapibus. Vivamus efficitur augue et urna mattis tristique. Sed sed libero justo. Suspendisse non sem convallis, lobortis arcu id, malesuada tortor. Aliquam eu congue libero. Mauris sit amet venenatis libero. Donec vitae purus dui. Sed vehicula ligula ut semper vulputate.Lorem ipsum dolor sit amet, consectetur adipiscing elit. Suspendisse at tincidunt ligula. Maecenas et velit vitae quam sollicitudin ullamcorper vitae nec ipsum. Sed vitae ullamcorper elit, sed lacinia libero. Aliquam vestibulum odio vitae nisi feugiat, mattis elementum est commodo. Fusce volutpat accumsan ultricies. Proin dapibus gravida porttitor. Aliquam consequat ex vitae mi tempus, et semper augue dapibus. Vivamus efficitur augue et urna mattis tristique. Sed sed libero justo. Suspendisse non sem convallis, lobortis arcu id, malesuada tortor. Aliquam eu congue libero. Mauris sit amet venenatis libero. Donec vitae purus dui. Sed vehicula ligula ut semper vulputate.Lorem ipsum dolor sit amet, consectetur adipiscing elit. Suspendisse at tincidunt ligula. Maecenas et velit vitae quam sollicitudin ullamcorper vitae nec ipsum. Sed vitae ullamcorper elit, sed lacinia libero. Aliquam vestibulum odio vitae nisi feugiat, mattis elementum est commodo. Fusce volutpat accumsan ultricies. Proin dapibus gravida porttitor. Aliquam consequat ex vitae mi tempus, et semper augue dapibus. Vivamus efficitur augue et urna mattis tristique. Sed sed libero justo. Suspendisse non sem convallis, lobortis arcu id, malesuada tortor. Aliquam eu congue libero. Mauris sit amet venenatis libero. Donec vitae purus dui. Sed vehicula ligula ut semper vulputate."
    }
  ],
  "comments": [
    {
      "id": "1",
      "text": "a comment regarding post 1",
      "postId": "1"
    },
    {
      "id": "2",
      "text": "another comment regarding post 1",
      "postId": "1"
    },
    {
      "id": "b0da",
      "postId": "1",
      "text": "sdfsdfs"
    },
    {
      "id": "4dcb",
      "postId": "1",
      "text": "wefwefwefwef"
    },
    {
      "id": "f55e",
      "postId": "1",
      "text": "sdfsdfsdf"
    },
    {
      "id": "4fce",
      "postId": "1",
      "text": "sdfsdfsdf"
    },
    {
      "id": "55ad",
      "postId": "1",
      "text": "sdfsdfsdfsdfsdfsdfsdf"
    },
    {
      "id": "6d3b",
      "postId": "3",
      "text": "dsfsdfsdf"
    },
    {
      "id": "0f03",
      "postId": "1",
      "text": "dfdfdf"
    },
    {
      "id": "c55c",
      "postId": "1",
      "text": "123"
    }
  ]
}
